{"autopilot_running": true, "last_loop_at": 1763581590.4424334, "validate_mode": "0", "equity_now_usd": 492.42, "equity_day_start_usd": 492.42, "equity_change_usd": -0.0, "paused": false, "cooldowns": {}, "symbols": [{"symbol": "ADA/USD", "price": 0.439635, "pos_qty": 0.0, "pos_value": 0.0}, {"symbol": "AAVE/USD", "price": 164.4, "pos_qty": 0.0, "pos_value": 0.0}, {"symbol": "ASTER/USD", "price": 1.27377, "pos_qty": 0.0, "pos_value": 0.0}, {"symbol": "AB/USD", "price": 0.006496, "pos_qty": 0.0, "pos_value": 0.0}, {"symbol": "AERO/USD", "price": 0.7532, "pos_qty": 0.0, "pos_value": 0.0}, {"symbol": "ALGO/USD", "price": 0.14603, "pos_qty": 0.0, "pos_value": 0.0}, {"symbol": "ARB/USD", "price": 0.2184, "pos_qty": 0.0, "pos_value": 0.0}, {"symbol": "AKE/USD", "price": 0.0003924, "pos_qty": 0.0, "pos_value": 0.0}, {"symbol": "AR/USD", "price": 4.01, "pos_qty": 0.0, "pos_value": 0.0}, {"symbol": "APT/USD", "price": 2.7258, "pos_qty": 0.0, "pos_value": 0.0}, {"symbol": "AI16Z/USD", "price": 0.0178, "pos_qty": 0.0, "pos_value": 0.0}, {"symbol": "AKT/USD", "price": 0.503, "pos_qty": 0.0, "pos_value": 0.0}, {"symbol": "APR/USD", "price": 0.2765, "pos_qty": 0.0, "pos_value": 0.0}, {"symbol": "1INCH/USD", "price": 0.1792, "pos_qty": 0.0, "pos_value": 0.0}, {"symbol": "ACH/USD", "price": 0.00956, "pos_qty": 0.0, "pos_value": 0.0}, {"symbol": "ALLO/USD", "price": 0.1582, "pos_qty": 0.0, "pos_value": 0.0}], "open_orders_preview": "(no open orders)", "pro_metrics": {"vol_annual_pct": 83.44, "sharpe_1h_30d": -571.58, "max_drawdown_pct": -36.41, "trend_strength": -0.0852, "price": 0.439635}, "last_actions": [], "ts": 1763581590.442479, "state_path": "/home/runner/workspace/state.json", "candle_tracking": {"BTC/USD": {"last_closed_ts": 1763233800000, "last_sma20": 96073.2, "last_close": 96075.0}, "ETH/USD": {"last_closed_ts": 1763233800000, "last_sma20": 3210.578, "last_close": 3208.22}, "ZEC/USD": {"last_closed_ts": 1763233800000, "last_sma20": 658.49, "last_close": 671.77}, "ADA/USD": {"last_closed_ts": 1763581200000, "last_sma20": 0.4409785999999999, "last_close": 0.439953}, "ALGO/USD": {"last_closed_ts": 1763581200000, "last_sma20": 0.1470565, "last_close": 0.14596}, "ASTER/USD": {"last_closed_ts": 1763581200000, "last_sma20": 1.2776859999999999, "last_close": 1.275}, "AAVE/USD": {"last_closed_ts": 1763581200000, "last_sma20": 164.7085, "last_close": 164.4}, "AERO/USD": {"last_closed_ts": 1763581200000, "last_sma20": 0.7559600000000002, "last_close": 0.7532}, "AB/USD": {"last_closed_ts": 1763581200000, "last_sma20": 0.0065158, "last_close": 0.006496}, "ARB/USD": {"last_closed_ts": 1763581200000, "last_sma20": 0.21971500000000002, "last_close": 0.2184}, "0G/USD": {"last_closed_ts": 1763411700000, "last_sma20": 1.1654000000000004, "last_close": 1.17}, "APT/USD": {"last_closed_ts": 1763581200000, "last_sma20": 2.731885, "last_close": 2.7258}, "ALCX/USD": {"last_closed_ts": 1763480400000, "last_sma20": 11.7095, "last_close": 12.15}, "1INCH/USD": {"last_closed_ts": 1763581200000, "last_sma20": 0.17956000000000003, "last_close": 0.1792}, "AR/USD": {"last_closed_ts": 1763581200000, "last_sma20": 3.996499999999999, "last_close": 4.0}, "AKT/USD": {"last_closed_ts": 1763581200000, "last_sma20": 0.5067900000000002, "last_close": 0.5032}, "AI16Z/USD": {"last_closed_ts": 1763581200000, "last_sma20": 0.018039999999999997, "last_close": 0.0176}, "AKE/USD": {"last_closed_ts": 1763581200000, "last_sma20": 0.00037941000000000006, "last_close": 0.0003902}, "ALLO/USD": {"last_closed_ts": 1763581500000, "last_sma20": 0.15721000000000002, "last_close": 0.1563}, "ACH/USD": {"last_closed_ts": 1763581500000, "last_sma20": 0.009596, "last_close": 0.00957}, "AIXBT/USD": {"last_closed_ts": 1763480400000, "last_sma20": 0.051885000000000014, "last_close": 0.0522}, "ARKM/USD": {"last_closed_ts": 1763480400000, "last_sma20": 0.27523, "last_close": 0.2786}, "A/USD": {"last_closed_ts": 1763420700000, "last_sma20": 0.23378000000000004, "last_close": 0.2347}, "APR/USD": {"last_closed_ts": 1763581200000, "last_sma20": 0.27418, "last_close": 0.2771}}, "autopilot_enabled": true}