{"autopilot_running": true, "last_loop_at": 1764630671.8869734, "validate_mode": "0", "equity_now_usd": 457.22, "equity_day_start_usd": 457.22, "equity_change_usd": 0.0, "paused": false, "cooldowns": {}, "symbols": [{"symbol": "BTC/USD", "price": 86553.8, "pos_qty": 0.0, "pos_value": 0.0}, {"symbol": "ETH/USD", "price": 2801.09, "pos_qty": 1.1637e-06, "pos_value": 0.0}, {"symbol": "SOL/USD", "price": 126.85, "pos_qty": 1.00705e-05, "pos_value": 0.0}, {"symbol": "XRP/USD", "price": 2.03674, "pos_qty": 0.0, "pos_value": 0.0}, {"symbol": "ADA/USD", "price": 0.384761, "pos_qty": 0.00299104, "pos_value": 0.0}, {"symbol": "DOGE/USD", "price": 0.1359492, "pos_qty": 0.0, "pos_value": 0.0}, {"symbol": "AVAX/USD", "price": 12.8, "pos_qty": 0.0, "pos_value": 0.0}, {"symbol": "POL/USD", "price": 0.12014, "pos_qty": 0.0, "pos_value": 0.0}, {"symbol": "DOT/USD", "price": 2.0434, "pos_qty": 9.46009e-05, "pos_value": 0.0}, {"symbol": "LINK/USD", "price": 12.10802, "pos_qty": 0.0, "pos_value": 0.0}, {"symbol": "UNI/USD", "price": 5.605, "pos_qty": 0.0, "pos_value": 0.0}, {"symbol": "ATOM/USD", "price": 2.2754, "pos_qty": 0.00114714, "pos_value": 0.0}, {"symbol": "LTC/USD", "price": 77.65, "pos_qty": 0.0, "pos_value": 0.0}, {"symbol": "ARB/USD", "price": 0.1933, "pos_qty": 0.0, "pos_value": 0.0}, {"symbol": "OP/USD", "price": 0.2871, "pos_qty": 0.0, "pos_value": 0.0}, {"symbol": "AAVE/USD", "price": 171.69, "pos_qty": 0.0, "pos_value": 0.0}, {"symbol": "ALGO/USD", "price": 0.13033, "pos_qty": 0.0, "pos_value": 0.0}, {"symbol": "APT/USD", "price": 1.871, "pos_qty": 0.0, "pos_value": 0.0}, {"symbol": "FIL/USD", "price": 1.485, "pos_qty": 0.0, "pos_value": 0.0}, {"symbol": "NEAR/USD", "price": 1.629, "pos_qty": 0.0, "pos_value": 0.0}], "open_orders_preview": "(no open orders)", "pro_metrics": {"vol_annual_pct": 52.94, "sharpe_1h_30d": -514.2, "max_drawdown_pct": -26.02, "trend_strength": -0.0044, "price": 86530.6}, "last_actions": [], "ts": 1764630671.8870513, "state_path": "/home/runner/workspace/state.json", "candle_tracking": {"BTC/USD": {"last_closed_ts": 1764630300000, "last_sma20": 86548.41000000002, "last_close": 86557.3}, "ETH/USD": {"last_closed_ts": 1764630300000, "last_sma20": 2799.0305, "last_close": 2800.54}, "ZEC/USD": {"last_closed_ts": 1763233800000, "last_sma20": 658.49, "last_close": 671.77}, "ADA/USD": {"last_closed_ts": 1764630300000, "last_sma20": 0.3829139, "last_close": 0.385014}, "ALGO/USD": {"last_closed_ts": 1764630300000, "last_sma20": 0.130501, "last_close": 0.13078}, "ASTER/USD": {"last_closed_ts": 1763657700000, "last_sma20": 1.2193859999999999, "last_close": 1.18189}, "AAVE/USD": {"last_closed_ts": 1764630300000, "last_sma20": 169.65349999999998, "last_close": 171.69}, "AERO/USD": {"last_closed_ts": 1763657700000, "last_sma20": 0.7555499999999999, "last_close": 0.7316}, "AB/USD": {"last_closed_ts": 1763657700000, "last_sma20": 0.006556149999999999, "last_close": 0.006519}, "ARB/USD": {"last_closed_ts": 1764630300000, "last_sma20": 0.19329999999999997, "last_close": 0.1933}, "0G/USD": {"last_closed_ts": 1763411700000, "last_sma20": 1.1654000000000004, "last_close": 1.17}, "APT/USD": {"last_closed_ts": 1764630300000, "last_sma20": 1.8671000000000002, "last_close": 1.871}, "ALCX/USD": {"last_closed_ts": 1763480400000, "last_sma20": 11.7095, "last_close": 12.15}, "1INCH/USD": {"last_closed_ts": 1763657700000, "last_sma20": 0.17887999999999998, "last_close": 0.1747}, "AR/USD": {"last_closed_ts": 1763657700000, "last_sma20": 4.1354999999999995, "last_close": 4.03}, "AKT/USD": {"last_closed_ts": 1763657700000, "last_sma20": 0.532515, "last_close": 0.5166}, "AI16Z/USD": {"last_closed_ts": 1763657700000, "last_sma20": 0.01702, "last_close": 0.0166}, "AKE/USD": {"last_closed_ts": 1763657700000, "last_sma20": 0.00042445999999999993, "last_close": 0.0004271}, "ALLO/USD": {"last_closed_ts": 1763657700000, "last_sma20": 0.155885, "last_close": 0.1488}, "ACH/USD": {"last_closed_ts": 1763657700000, "last_sma20": 0.0097965, "last_close": 0.00961}, "AIXBT/USD": {"last_closed_ts": 1763480400000, "last_sma20": 0.051885000000000014, "last_close": 0.0522}, "ARKM/USD": {"last_closed_ts": 1763480400000, "last_sma20": 0.27523, "last_close": 0.2786}, "A/USD": {"last_closed_ts": 1763420700000, "last_sma20": 0.23378000000000004, "last_close": 0.2347}, "APR/USD": {"last_closed_ts": 1763657700000, "last_sma20": 0.2787035000000001, "last_close": 0.27402}, "SOL/USD": {"last_closed_ts": 1764630300000, "last_sma20": 126.4965, "last_close": 126.92}, "XRP/USD": {"last_closed_ts": 1764630300000, "last_sma20": 2.0317805, "last_close": 2.03566}, "DOGE/USD": {"last_closed_ts": 1764630300000, "last_sma20": 0.135596585, "last_close": 0.1359545}, "AVAX/USD": {"last_closed_ts": 1764630300000, "last_sma20": 12.7995, "last_close": 12.81}, "DOT/USD": {"last_closed_ts": 1764630300000, "last_sma20": 2.0373900000000003, "last_close": 2.0434}, "LINK/USD": {"last_closed_ts": 1764630300000, "last_sma20": 12.074941500000003, "last_close": 12.1252}, "UNI/USD": {"last_closed_ts": 1764630300000, "last_sma20": 5.5825499999999995, "last_close": 5.605}, "ATOM/USD": {"last_closed_ts": 1764630300000, "last_sma20": 2.26082, "last_close": 2.2785}, "LTC/USD": {"last_closed_ts": 1764630300000, "last_sma20": 77.4665, "last_close": 77.67}, "OP/USD": {"last_closed_ts": 1764630300000, "last_sma20": 0.28722499999999995, "last_close": 0.2871}, "FIL/USD": {"last_closed_ts": 1764630300000, "last_sma20": 1.49335, "last_close": 1.492}, "NEAR/USD": {"last_closed_ts": 1764630300000, "last_sma20": 1.63295, "last_close": 1.63}, "POL/USD": {"last_closed_ts": 1764630300000, "last_sma20": 0.11995200000000002, "last_close": 0.12017}}, "autopilot_enabled": true}